dmarc/__init__.py
dmarc/rua.xsd
dmarc/rua_mod.xsd
dmarc/s3.py
dmarc_import-1.1.1.dist-info/LICENSE.md
dmarc_import-1.1.1.dist-info/METADATA
dmarc_import-1.1.1.dist-info/WHEEL
dmarc_import-1.1.1.dist-info/entry_points.txt
dmarc_import-1.1.1.dist-info/top_level.txt
dmarc_import-1.1.1.dist-info/RECORD
