Metadata-Version: 2.1
Name: dmarc-import
Version: 1.1.1
Summary: A tool for parsing DMARC aggregate reports
Home-page: https://www.us-cert.gov/resources/ncats
Author: Cyber and Infrastructure Security Agency
Author-email: ncats@hq.dhs.gov
License: License :: CC0 1.0 Universal (CC0 1.0) Public Domain Dedication
Download-URL: https://github.com/cisagov/dmarc-import
Keywords: dmarc,rua
Platform: UNKNOWN
Classifier: Development Status :: 3 - Alpha
Classifier: Intended Audience :: Developers
Classifier: License :: CC0 1.0 Universal (CC0 1.0) Public Domain Dedication
Classifier: Programming Language :: Python :: 3
Classifier: Programming Language :: Python :: 3.4
Classifier: Programming Language :: Python :: 3.5
Classifier: Programming Language :: Python :: 3.6
Requires-Dist: boto3 (>=1.4.7)
Requires-Dist: docopt (>=0.6.2)
Requires-Dist: lxml (==4.1.1)
Requires-Dist: requests (>=2.18.4)
Requires-Dist: requests-aws4auth (>=0.9)
Requires-Dist: xmljson (>=0.1.9)
Provides-Extra: dev
Requires-Dist: check-manifest (>=0.36) ; extra == 'dev'
Requires-Dist: pytest (>=3.5.0) ; extra == 'dev'
Requires-Dist: semver (>=2.7.9) ; extra == 'dev'
Requires-Dist: tox (>=3.0.0) ; extra == 'dev'
Requires-Dist: wheel (>=0.31.0) ; extra == 'dev'
